{
	"$schema": "http://schema.management.azure.com/schemas/2015-01-01/deploymentTemplate.json#",
	"contentVersion": "1.0.0.0",
	"parameters": {
		"factoryName": {
			"type": "string",
			"metadata": "Data Factory name",
			"defaultValue": "Group26"
		}
	},
	"variables": {
		"factoryId": "[concat('Microsoft.DataFactory/factories/', parameters('factoryName'))]"
	},
	"resources": [
		{
			"name": "[concat(parameters('factoryName'), '/CopyPipeline_hkd')]",
			"type": "Microsoft.DataFactory/factories/pipelines",
			"apiVersion": "2018-06-01",
			"properties": {
				"activities": [
					{
						"name": "Copy_hkd",
						"type": "Copy",
						"dependsOn": [],
						"policy": {
							"timeout": "7.00:00:00",
							"retry": 0,
							"retryIntervalInSeconds": 30,
							"secureOutput": false,
							"secureInput": false
						},
						"userProperties": [
							{
								"name": "Source",
								"value": "/Clientes.csv"
							},
							{
								"name": "Destination",
								"value": "Clientes"
							}
						],
						"typeProperties": {
							"source": {
								"type": "DelimitedTextSource",
								"storeSettings": {
									"type": "FileServerReadSettings",
									"recursive": true,
									"enablePartitionDiscovery": false
								},
								"formatSettings": {
									"type": "DelimitedTextReadSettings",
									"skipLineCount": 0
								}
							},
							"sink": {
								"type": "AzureSqlSink",
								"tableOption": "autoCreate"
							},
							"enableStaging": false,
							"validateDataConsistency": false,
							"translator": {
								"type": "TabularTranslator",
								"mappings": [
									{
										"source": {
											"name": "Cliente ID",
											"type": "String",
											"physicalType": "String"
										},
										"sink": {
											"name": "Cliente ID",
											"type": "String"
										}
									},
									{
										"source": {
											"name": "Nombre",
											"type": "String",
											"physicalType": "String"
										},
										"sink": {
											"name": "Nombre",
											"type": "String"
										}
									},
									{
										"source": {
											"name": "Apellido",
											"type": "String",
											"physicalType": "String"
										},
										"sink": {
											"name": "Apellido",
											"type": "String"
										}
									},
									{
										"source": {
											"name": "Segmento",
											"type": "String",
											"physicalType": "String"
										},
										"sink": {
											"name": "Segmento",
											"type": "String"
										}
									}
								],
								"typeConversion": true,
								"typeConversionSettings": {
									"allowDataTruncation": true,
									"treatBooleanAsNumber": false
								}
							}
						},
						"inputs": [
							{
								"referenceName": "SourceDataset_hkd",
								"type": "DatasetReference"
							}
						],
						"outputs": [
							{
								"referenceName": "DestinationDataset_hkd",
								"type": "DatasetReference"
							}
						]
					}
				],
				"annotations": []
			},
			"dependsOn": [
				"[concat(variables('factoryId'), '/datasets/SourceDataset_hkd')]",
				"[concat(variables('factoryId'), '/datasets/DestinationDataset_hkd')]"
			]
		},
		{
			"name": "[concat(parameters('factoryName'), '/DestinationDataset_hkd')]",
			"type": "Microsoft.DataFactory/factories/datasets",
			"apiVersion": "2018-06-01",
			"properties": {
				"linkedServiceName": {
					"referenceName": "SQLDBGrupo26",
					"type": "LinkedServiceReference"
				},
				"annotations": [],
				"type": "AzureSqlTable",
				"schema": [],
				"typeProperties": {
					"schema": "Clientes",
					"table": "File system file"
				}
			},
			"dependsOn": []
		},
		{
			"name": "[concat(parameters('factoryName'), '/SourceDataset_hkd')]",
			"type": "Microsoft.DataFactory/factories/datasets",
			"apiVersion": "2018-06-01",
			"properties": {
				"linkedServiceName": {
					"referenceName": "FileServer202",
					"type": "LinkedServiceReference"
				},
				"annotations": [],
				"type": "DelimitedText",
				"typeProperties": {
					"location": {
						"type": "FileServerLocation",
						"fileName": "Clientes.csv"
					},
					"columnDelimiter": ",",
					"escapeChar": "\\",
					"firstRowAsHeader": true,
					"quoteChar": "\""
				},
				"schema": [
					{
						"name": "Cliente ID",
						"type": "String"
					},
					{
						"name": "Nombre",
						"type": "String"
					},
					{
						"name": "Apellido",
						"type": "String"
					},
					{
						"name": "Segmento",
						"type": "String"
					}
				]
			},
			"dependsOn": []
		}
	]
}